{
  "id": "unit-circle",
  "name": "Unit Circle",
  "latex": "x^2 + y^2 = 1, \\quad \\cos \\theta = x, \\quad \\sin \\theta = y",
  "explanation": "The unit circle is a circle with radius 1 centered at the origin. It's fundamental to trigonometry because any point on the unit circle has coordinates (cos \u03b8, sin \u03b8), where \u03b8 is the angle from the positive x-axis. This connects trigonometric functions to coordinates and makes it easy to find exact values for common angles.",
  "examples": [
    {
      "problem": "Find cos(0\u00b0) and sin(0\u00b0)",
      "solution": "cos(0\u00b0) = 1, sin(0\u00b0) = 0",
      "steps": [
        "At 0\u00b0, the point on the unit circle is (1, 0)",
        "cos(0\u00b0) = x-coordinate = 1",
        "sin(0\u00b0) = y-coordinate = 0"
      ]
    },
    {
      "problem": "Find cos(90\u00b0) and sin(90\u00b0)",
      "solution": "cos(90\u00b0) = 0, sin(90\u00b0) = 1",
      "steps": [
        "At 90\u00b0, the point on the unit circle is (0, 1)",
        "cos(90\u00b0) = x-coordinate = 0",
        "sin(90\u00b0) = y-coordinate = 1"
      ]
    },
    {
      "problem": "Find cos(45\u00b0) and sin(45\u00b0)",
      "solution": "cos(45\u00b0) = sin(45\u00b0) = \u221a2/2",
      "steps": [
        "At 45\u00b0, the point is (\u221a2/2, \u221a2/2)",
        "cos(45\u00b0) = sin(45\u00b0) = \u221a2/2 \u2248 0.707"
      ]
    }
  ],
  "prerequisites": [
    "soh-cah-toa",
    "pythagorean-theorem"
  ],
  "related": [
    "soh-cah-toa",
    "trig-identities"
  ],
  "level": "geometry",
  "tags": [
    "trigonometry",
    "unit-circle",
    "coordinates"
  ],
  "topic": "trigonometry",
  "proof": "Unit circle: x\u00b2 + y\u00b2 = 1. Point at angle \u03b8: (cos(\u03b8), sin(\u03b8)). Proof: In right triangle with hypotenuse 1, opposite = sin(\u03b8), adjacent = cos(\u03b8). Coordinates satisfy x\u00b2 + y\u00b2 = cos\u00b2(\u03b8) + sin\u00b2(\u03b8) = 1. All trig functions defined from unit circle."
}